scriptit/__init__.py
scriptit/_version.py
scriptit/app.py
scriptit/color.py
scriptit/refresh_printer.py
scriptit/shape.py
scriptit/size.py
script_it-0.2.0.dist-info/METADATA
script_it-0.2.0.dist-info/WHEEL
script_it-0.2.0.dist-info/top_level.txt
script_it-0.2.0.dist-info/RECORD
